.DS_Store
tgmagic/__init__.py
tgmagic/bot.py
tgmagic/buttons.py
tgmagic/helper.py
tgmagic/menu.py
tgmagic-1.0.dist-info/DESCRIPTION.rst
tgmagic-1.0.dist-info/METADATA
tgmagic-1.0.dist-info/RECORD
tgmagic-1.0.dist-info/WHEEL
tgmagic-1.0.dist-info/metadata.json
tgmagic-1.0.dist-info/top_level.txt
