Metadata-Version: 2.0
Name: tgmagic
Version: 1.0
Summary: Module for multi-level menu in telegram bots based on "python-telegram-bot" Edit
Home-page: https://github.com/tezmen/tg-magic
Author: tezmen
Author-email: tezmenpro@gmail.com
License: Apache License, Version 2.0, see LICENSE file
Download-URL: https://github.com/tezmen/tg-magic/archive/master.zip
Keywords: telegram,bot,keyboard,simple,multi-level,three,menu
Platform: UNKNOWN
Classifier: License :: OSI Approved :: Apache Software License
Classifier: Operating System :: OS Independent
Classifier: Environment :: Console
Classifier: Development Status :: 3 - Alpha
Classifier: Programming Language :: Python
Classifier: Programming Language :: Python :: 3
Classifier: Programming Language :: Python :: 3.4
Classifier: Programming Language :: Python :: 3.5
Classifier: Programming Language :: Python :: 3.6
Classifier: Programming Language :: Python :: Implementation :: PyPy
Classifier: Programming Language :: Python :: Implementation :: CPython
Requires-Dist: dpath (>=1.3.0)
Requires-Dist: python-telegram-bot (>=5.0)
Requires-Dist: requests (>=2.0)
